statex/__init__.py
statex/statex.py
statex-0.1.0.dist-info/LICENSE
statex-0.1.0.dist-info/METADATA
statex-0.1.0.dist-info/WHEEL
statex-0.1.0.dist-info/RECORD
